oak_mcp/__init__.py
oak_mcp/__main__.py
oak_mcp/_version.py
oak_mcp/main.py
oak_mcp-0.1.16.dist-info/METADATA
oak_mcp-0.1.16.dist-info/WHEEL
oak_mcp-0.1.16.dist-info/entry_points.txt
oak_mcp-0.1.16.dist-info/RECORD
