Metadata-Version: 2.4
Name: oak-mcp
Version: 0.1.16
Summary: A model context protocol (MCP) to help agents interact with ontologies and the ontology access kit
Project-URL: Homepage, https://github.com/monarch-initiative/oak-mcp
Project-URL: Repository, https://github.com/monarch-initiative/oak-mcp
Project-URL: Issues, https://github.com/monarch-initiative/oak-mcp/issues
Project-URL: Documentation, https://github.com/monarch-initiative/oak-mcp#readme
Author-email: Justin Reese <justaddcoffee@gmail.com>, Mark Andrew Miller <MAM@lbl.gov>
License: MIT
Keywords: bioinformatics,mcp,oak,ontology
Classifier: Development Status :: 4 - Beta
Classifier: Intended Audience :: Developers
Classifier: Intended Audience :: Science/Research
Classifier: License :: OSI Approved :: MIT License
Classifier: Operating System :: OS Independent
Classifier: Programming Language :: Python :: 3
Classifier: Programming Language :: Python :: 3.11
Classifier: Programming Language :: Python :: 3.12
Classifier: Topic :: Scientific/Engineering
Classifier: Topic :: Software Development :: Libraries :: Python Modules
Requires-Python: >=3.11
Requires-Dist: fastmcp>=2.7.1
Requires-Dist: oaklib>=0.5.18
